ejgpu/__init__.py
ejgpu/logging_utils.py
ejgpu/triton_kernels/__init__.py
ejgpu/triton_kernels/decode_attention/__init__.py
ejgpu/triton_kernels/decode_attention/_interface.py
ejgpu/triton_kernels/decode_attention/_triton_impl_fwd.py
ejgpu/triton_kernels/flash_attn/__init__.py
ejgpu/triton_kernels/flash_attn/_interface.py
ejgpu/triton_kernels/flash_attn/_triton_impl_bwd.py
ejgpu/triton_kernels/flash_attn/_triton_impl_fwd.py
ejgpu/triton_kernels/flash_attn/_utilities.py
ejgpu/triton_kernels/flash_attn_varlen/__init__.py
ejgpu/triton_kernels/flash_attn_varlen/_interface.py
ejgpu/triton_kernels/flash_attn_varlen/_triton_impl_bwd.py
ejgpu/triton_kernels/flash_attn_varlen/_triton_impl_fwd_decode.py
ejgpu/triton_kernels/flash_attn_varlen/_triton_impl_fwd_prefill.py
ejgpu/triton_kernels/flash_attn_varlen/_vanilla.py
ejgpu/triton_kernels/flash_mla/__init__.py
ejgpu/triton_kernels/flash_mla/_interface.py
ejgpu/triton_kernels/flash_mla/_triton_impl_bwd.py
ejgpu/triton_kernels/flash_mla/_triton_impl_fwd.py
ejgpu/triton_kernels/flash_mla/_utilities.py
ejgpu/triton_kernels/gla/__init__.py
ejgpu/triton_kernels/gla/_interface.py
ejgpu/triton_kernels/lightning_attn/__init__.py
ejgpu/triton_kernels/lightning_attn/_interface.py
ejgpu/triton_kernels/mean_pooling/__init__.py
ejgpu/triton_kernels/mean_pooling/_interface.py
ejgpu/triton_kernels/mean_pooling/_triton_impl_bwd.py
ejgpu/triton_kernels/mean_pooling/_triton_impl_fwd.py
ejgpu/triton_kernels/native_spare_attention/__init__.py
ejgpu/triton_kernels/native_spare_attention/_compression.py
ejgpu/triton_kernels/native_spare_attention/_interface.py
ejgpu/triton_kernels/native_spare_attention/_triton_impl_bwd.py
ejgpu/triton_kernels/native_spare_attention/_triton_impl_fwd.py
ejgpu/triton_kernels/native_spare_attention/_utilities.py
ejgpu/triton_kernels/recurrent/__init__.py
ejgpu/triton_kernels/recurrent/_interface.py
ejgpu/triton_kernels/recurrent/_triton_impl_bwd.py
ejgpu/triton_kernels/recurrent/_triton_impl_fwd.py
ejgpu/utils.py
ejgpu-0.0.1.dist-info/LICENSE
ejgpu-0.0.1.dist-info/METADATA
ejgpu-0.0.1.dist-info/WHEEL
ejgpu-0.0.1.dist-info/RECORD
