Metadata-Version: 2.3
Name: ejgpu
Version: 0.0.1
Summary: ejgpu
License: Apache-2.0
Keywords: EasyDeL
Author: Erfan Zare Chavoshi
Author-email: Erfanzare810@gmail.com
Requires-Python: >=3.10,<3.14
Classifier: Development Status :: 3 - Alpha
Classifier: Intended Audience :: Developers
Classifier: License :: OSI Approved :: Apache Software License
Classifier: Programming Language :: Python :: 3
Classifier: Programming Language :: Python :: 3.10
Classifier: Programming Language :: Python :: 3.11
Classifier: Programming Language :: Python :: 3.12
Classifier: Programming Language :: Python :: 3.13
Classifier: Topic :: Scientific/Engineering :: Artificial Intelligence
Requires-Dist: eformer (>=0.0.41)
Requires-Dist: jax (>=0.6.0)
Requires-Dist: jaxlib (>=0.6.0)
Requires-Dist: jaxtyping (>=0.3.2,<0.4.0)
Requires-Dist: triton (>=3.2.0,<3.3.0)
Project-URL: Documentation, https://ejgpu.readthedocs.io/en/latest/
Project-URL: Homepage, https://github.com/erfanzar/ejgpu
Project-URL: Repository, https://github.com/erfanzar/ejgpu
